ait/__init__.py
ait/factories.py
ait/adapters/__init__.py
ait/adapters/instructor_adapter.py
ait/adapters/jinja2_adapter.py
ait/adapters/pydantic_adapter.py
ait/core/base.py
ait/core/tools.py
ait/core/utils.py
ait/core/domain/errors.py
ait/core/domain/interfaces.py
ait/core/ports/__init__.py
ait/core/ports/formatter_port.py
ait/core/ports/llm_port.py
ait/core/ports/modeller_port.py
ait/core/ports/workflow_port.py
grafo_ai_tools-0.1.3.dist-info/licenses/LICENSE.txt
grafo_ai_tools-0.1.3.dist-info/METADATA
grafo_ai_tools-0.1.3.dist-info/WHEEL
grafo_ai_tools-0.1.3.dist-info/top_level.txt
grafo_ai_tools-0.1.3.dist-info/RECORD
