Metadata-Version: 2.4
Name: grafo-ai-tools
Version: 0.1.3
Summary: A set of tools for easily interacting with LLMs.
Author-email: "@paulomtts" <paulomtts@outlook.com>
License: MIT
Project-URL: Homepage, https://github.com/paulomtts/Grafo-AI-Tools.git
Keywords: ai,agents,llm,workflows
Classifier: Intended Audience :: Developers
Classifier: Programming Language :: Python :: 3.11
Classifier: License :: OSI Approved :: MIT License
Classifier: Operating System :: OS Independent
Requires-Python: >=3.11
License-File: LICENSE.txt
Requires-Dist: build>=1.3.0
Requires-Dist: bump2version>=1.0.1
Requires-Dist: grafo>=0.2.36
Requires-Dist: instructor>=1.11.2
Requires-Dist: pytest>=8.4.1
Requires-Dist: pytest-asyncio>=1.1.0
Requires-Dist: pyyaml>=6.0.2
Dynamic: license-file
